MANIFEST.in
README
setup.py
downward_dlr/CHANGES.md
downward_dlr/LICENSE.md
downward_dlr/README.md
downward_dlr/__init__.py
downward_dlr/build.py
downward_dlr/build_configs.py
downward_dlr/downward_dlr.py
downward_dlr/fast-downward.py
downward_dlr.egg-info/PKG-INFO
downward_dlr.egg-info/SOURCES.txt
downward_dlr.egg-info/dependency_links.txt
downward_dlr.egg-info/entry_points.txt
downward_dlr.egg-info/top_level.txt
downward_dlr/driver/__init__.py
downward_dlr/driver/aliases.py
downward_dlr/driver/arguments.py
downward_dlr/driver/call.py
downward_dlr/driver/cleanup.py
downward_dlr/driver/limits.py
downward_dlr/driver/main.py
downward_dlr/driver/plan_manager.py
downward_dlr/driver/portfolio_runner.py
downward_dlr/driver/returncodes.py
downward_dlr/driver/run_components.py
downward_dlr/driver/tests.py
downward_dlr/driver/util.py
downward_dlr/driver/version.py
downward_dlr/driver/portfolios/seq_opt_fdss_1.py
downward_dlr/driver/portfolios/seq_opt_fdss_2.py
downward_dlr/driver/portfolios/seq_opt_merge_and_shrink.py
downward_dlr/driver/portfolios/seq_sat_fdss_1.py
downward_dlr/driver/portfolios/seq_sat_fdss_2.py
downward_dlr/driver/portfolios/seq_sat_fdss_2014.py
downward_dlr/driver/portfolios/seq_sat_fdss_2018.py
downward_dlr/src/CMakeLists.txt
downward_dlr/src/cmake_modules/FastDownwardMacros.cmake
downward_dlr/src/cmake_modules/FindClp.cmake
downward_dlr/src/cmake_modules/FindCplex.cmake
downward_dlr/src/cmake_modules/FindOSI.cmake
downward_dlr/src/search/CMakeLists.txt
downward_dlr/src/search/DownwardFiles.cmake
downward_dlr/src/search/abstract_task.cc
downward_dlr/src/search/abstract_task.h
downward_dlr/src/search/axioms.cc
downward_dlr/src/search/axioms.h
downward_dlr/src/search/command_line.cc
downward_dlr/src/search/command_line.h
downward_dlr/src/search/evaluation_context.cc
downward_dlr/src/search/evaluation_context.h
downward_dlr/src/search/evaluation_result.cc
downward_dlr/src/search/evaluation_result.h
downward_dlr/src/search/evaluator.cc
downward_dlr/src/search/evaluator.h
downward_dlr/src/search/evaluator_cache.cc
downward_dlr/src/search/evaluator_cache.h
downward_dlr/src/search/global_state.cc
downward_dlr/src/search/global_state.h
