Metadata-Version: 1.1
Name: downward-dlr
Version: 19.6.1
Summary: downward_dlr is a fork of the Fast-Downward Planning System (www.fast-downward.org)
Home-page: UNKNOWN
Author: Christoph Suerig
Author-email: christoph.suerig@dlr.de
License: GNU General Public License Version 3
Keywords: semantic planning pddl fast downward planner fast-downward domain-independent
Platform: UNKNOWN
Classifier: Programming Language :: Python :: 2.7
Classifier: Programming Language :: C++
Classifier: Environment :: Console
Classifier: License :: OSI Approved :: GNU General Public License v3 (GPLv3)
Classifier: Topic :: Scientific/Engineering
